kcwebps
kcwebps/common
kcwebps/config
kcwebps/index
kcwebps/index/common
kcwebps/index/common/file
kcwebps/index/common/file/sqlite
kcwebps/index/controller
kcwebps/index/controller/index
kcwebps/index/controller/index/app
kcwebps/index/controller/index/app/runtime
kcwebps/index/controller/index/app/runtime/cachepath
kcwebps/index/controller/index/common
kcwebps/index/controller/index/common/file
kcwebps/index/controller/index/common/file/sqlite
kcwebps/index/controller/index/tpl
kcwebps/index/controller/index/tpl/admin
kcwebps/index/controller/index/tpl/index
kcwebps/index/controller/index/tpl/menu
kcwebps/index/controller/index/tpl/modular
kcwebps/index/controller/index/tpl/plan
kcwebps/index/controller/index/tpl/plug
kcwebps/index/controller/index/tpl/setup
kcwebps/index/controller/index/tpl/socket
kcwebps/index/controller/index/tpl/task
kcwebps/index/controller/index/tplm
kcwebps/index/controller/index/tplm/admin
kcwebps/index/controller/index/tplm/include
kcwebps/index/controller/index/tplm/index
kcwebps/index/controller/index/tplm/menu
kcwebps/index/controller/index/tplm/modular
kcwebps/index/controller/index/tplm/plan
kcwebps/index/controller/index/tplm/plug
kcwebps/index/controller/index/tplm/setup
kcwebps/index/controller/index/tplm/task
kcwebps/tempfile
kcwebps/tempfile/kcwebps
kcwebps/tempfile/kcwebps/app
kcwebps/tempfile/kcwebps/app/common
kcwebps/tempfile/kcwebps/app/common/file
kcwebps/tempfile/kcwebps/app/common/file/sqlite
kcwebps/tempfile/kcwebps/app/common/html
kcwebps/tempfile/kcwebps/app/common/html/include
kcwebps/tempfile/kcwebps/app/intapp
kcwebps/tempfile/kcwebps/app/intapp/common
kcwebps/tempfile/kcwebps/app/intapp/common/file
kcwebps/tempfile/kcwebps/app/intapp/common/file/sqlite
kcwebps/tempfile/kcwebps/app/intapp/controller
kcwebps/tempfile/kcwebps/app/intapp/controller/index
kcwebps/tempfile/kcwebps/app/intapp/controller/index/common
kcwebps/tempfile/kcwebps/app/intapp/controller/index/common/file
